bgotd.py
bgotd-1.0.0.dist-info/METADATA
bgotd-1.0.0.dist-info/WHEEL
bgotd-1.0.0.dist-info/entry_points.txt
bgotd-1.0.0.dist-info/licenses/LICENSE
bgotd-1.0.0.dist-info/RECORD
