Metadata-Version: 2.4
Name: bgotd
Version: 1.0.0
Summary: Background of the day script.
Project-URL: Homepage, https://khws.io
Author-email: Kurt Stolle <kurt@khws.io>
License-Expression: MIT
License-File: LICENSE
Classifier: Operating System :: OS Independent
Classifier: Programming Language :: Python :: 3
Requires-Python: >=3.12
Requires-Dist: beautifulsoup4
Requires-Dist: curl-cffi
Requires-Dist: lxml
Requires-Dist: requests
